Ninja/Ninja_Finder.py
Ninja/__init__.py
IMSmartFinderNinja-0.1.2.dist-info/LICENSE
IMSmartFinderNinja-0.1.2.dist-info/METADATA
IMSmartFinderNinja-0.1.2.dist-info/WHEEL
IMSmartFinderNinja-0.1.2.dist-info/top_level.txt
IMSmartFinderNinja-0.1.2.dist-info/RECORD
