Metadata-Version: 2.1
Name: IMSmartFinderNinja
Version: 0.1.2
Summary: this version is for smart solution for data quality Assuracne Engineering automation
Home-page: https://github.com/Mohamed-ElhajAbdou/IMSmartFinderNinja
Author: Mohamed Elhajabdou
Author-email: mohamedelsayedmohammed.2020@gmail.com
Project-URL: Bug Tracker, https://github.com/Mohamed-ElhajAbdou/IMSmartFinderNinja/issues
Classifier: Programming Language :: Python :: 3
Classifier: License :: OSI Approved :: MIT License
Classifier: Operating System :: OS Independent
Requires-Python: >=3.6
License-File: LICENSE
